jetfactory/__init__.py
jetfactory/__version__.py
jetfactory/db.py
jetfactory/exceptions.py
jetfactory/log.py
jetfactory/registry.py
jetfactory/schema.py
jetfactory/utils.py
jetfactory/controller/__init__.py
jetfactory/controller/base.py
jetfactory/controller/decorators.py
jetfactory/controller/injector.py
jetfactory/core/__init__.py
jetfactory/core/app.py
jetfactory/core/component.py
jetfactory/core/error.py
jetfactory/core/manager.py
jetfactory/core/package.py
jetfactory/core/settings.py
jetfactory/service/__init__.py
jetfactory/service/base.py
jetfactory/service/db.py
jetfactory/service/http.py
jetfactory-0.2.0.dist-info/LICENSE
jetfactory-0.2.0.dist-info/METADATA
jetfactory-0.2.0.dist-info/WHEEL
jetfactory-0.2.0.dist-info/entry_points.txt
jetfactory-0.2.0.dist-info/top_level.txt
jetfactory-0.2.0.dist-info/RECORD
