Metadata-Version: 2.1
Name: jetfactory
Version: 0.2.0
Summary: Framework for building Web APIs using asyncio
Home-page: https://github.com/rbw/jetfactory
Author: Robert Wikman
Author-email: rbw@vault13.org
License: BSD-2
Platform: UNKNOWN
Classifier: Programming Language :: Python
Classifier: Programming Language :: Python :: 3.6
Classifier: Programming Language :: Python :: 3.7
Classifier: Programming Language :: Python :: Implementation :: CPython
Requires-Python: >=3.6
